qtazu/__init__.py
qtazu/__version__.py
qtazu/utils.py
qtazu/models/__init__.py
qtazu/models/persons.py
qtazu/res/icon/camera.png
qtazu/res/icon/no_thumbnail.png
qtazu/res/image/logo_kitsu.png
qtazu/widgets/__init__.py
qtazu/widgets/comment.py
qtazu/widgets/login.py
qtazu/widgets/screenmarquee.py
qtazu/widgets/taskbreadcrumb.py
qtazu/widgets/thumbnail.py
qtazu-0.1.4.dist-info/LICENSE
qtazu-0.1.4.dist-info/METADATA
qtazu-0.1.4.dist-info/WHEEL
qtazu-0.1.4.dist-info/top_level.txt
qtazu-0.1.4.dist-info/RECORD
