Metadata-Version: 2.1
Name: qtazu
Version: 0.1.4
Summary: Python Qt widgets for CG-Wire using gazu
Home-page: https://github.com/Colorbleed/qtazu
Author: CG Wire
Author-email: roy_nieterau@hotmail.com
License: MIT
Keywords: cg,production,asset manager,asset,shot,tasks,tracking
Platform: UNKNOWN
Classifier: Development Status :: 5 - Production/Stable
Classifier: Intended Audience :: Developers
Classifier: Natural Language :: English
Classifier: Programming Language :: Python :: 2.7
Classifier: Programming Language :: Python :: 3.4
Classifier: Programming Language :: Python :: 3.5
Classifier: Programming Language :: Python :: 3.6
Classifier: Programming Language :: Python :: Implementation :: CPython
Classifier: Programming Language :: Python :: Implementation :: PyPy
Classifier: Topic :: Multimedia :: Graphics
License-File: LICENSE
Requires-Dist: qt.py (>=1.2.3)
Requires-Dist: gazu (>=0.7.14)
Provides-Extra: dev
Requires-Dist: wheel ; extra == 'dev'
Provides-Extra: test
Requires-Dist: pytest ; extra == 'test'
Requires-Dist: pytest-cov ; extra == 'test'
Requires-Dist: requests-mock ; extra == 'test'
